optimal/__init__.py
optimal/client_gui.py
optimal/coord.py
optimal/cubie.py
optimal/defs.py
optimal/enums.py
optimal/face.py
optimal/misc.py
optimal/moves.py
optimal/performance.py
optimal/pruning.py
optimal/solver.py
optimal/symmetries.py
RubikOptimal-1.0.8.dist-info/LICENSE
RubikOptimal-1.0.8.dist-info/METADATA
RubikOptimal-1.0.8.dist-info/WHEEL
RubikOptimal-1.0.8.dist-info/top_level.txt
RubikOptimal-1.0.8.dist-info/RECORD
