Metadata-Version: 2.1
Name: RubikOptimal
Version: 1.0.8
Summary: A package to optimally solve Rubik's cube.
Home-page: https://github.com/hkociemba/RubiksCube-OptimalSolver
Author: Herbert Kociemba
Author-email: kociemba@t-online.de
License: UNKNOWN
Project-URL: Bug Tracker, https://github.com/hkociemba/RubiksCube-OptimalSolver/issues
Keywords: 'Rubik's Cube,Rubik,cube,solver,optimal,algorithm,Kociemba'
Platform: UNKNOWN
Classifier: Programming Language :: Python :: 3
Classifier: License :: OSI Approved :: GNU General Public License v3 or later (GPLv3+)
Classifier: Operating System :: OS Independent
Requires-Python: >=3.4
License-File: LICENSE
